{"is_source_file": true, "format": "TypeScript", "description": "This is a main entry point file for an Angular application, responsible for bootstrapping the root component with the application configuration.", "external_files": ["@angular/platform-browser", "./app/app.config", "./app/app.component"], "external_methods": ["bootstrapApplication"], "published": [], "classes": [], "methods": [{"name": "bootstrapApplication", "description": "Bootstraps the Angular application with the specified root component and configuration."}], "calls": ["bootstrapApplication(AppComponent, appConfig)", "console.error(err)"], "search-terms": ["main.ts", "Angular bootstrap", "AppComponent", "appConfig", "bootstrapApplication", "Angular application entry point"], "state": 2, "file_id": 8, "knowledge_revision": 36, "git_revision": "cbbe7f3bbb7b4b3bbe240a2f18ff4930aa33edcc", "ctags": [], "hash": "c986c915181c0d91d6ea1af9fc003131", "format-version": 4, "code-base-name": "frontend_notes", "filename": "frontend_notes/src/main.ts", "revision_history": [{"36": "cbbe7f3bbb7b4b3bbe240a2f18ff4930aa33edcc"}]}